json2graph/__init__.py
json2graph/json2graph.py
json2graph-0.2.0.dist-info/licenses/LICENSE
json2graph-0.2.0.dist-info/METADATA
json2graph-0.2.0.dist-info/WHEEL
json2graph-0.2.0.dist-info/top_level.txt
json2graph-0.2.0.dist-info/RECORD
