Metadata-Version: 2.4
Name: json2graph
Version: 0.2.0
Summary: A Python library to automatically import JSON to FalkorDB as a Graph
Author: FalkorDB
License: MIT
Project-URL: Homepage, https://github.com/FalkorDB/json2graph
Project-URL: Repository, https://github.com/FalkorDB/json2graph
Project-URL: Issues, https://github.com/FalkorDB/json2graph/issues
Keywords: falkordb,json,graph,database,import,converter
Classifier: Development Status :: 3 - Alpha
Classifier: Intended Audience :: Developers
Classifier: Topic :: Database
Classifier: License :: OSI Approved :: MIT License
Classifier: Programming Language :: Python :: 3
Classifier: Programming Language :: Python :: 3.10
Classifier: Programming Language :: Python :: 3.11
Classifier: Programming Language :: Python :: 3.12
Classifier: Programming Language :: Python :: 3.13
Requires-Python: >=3.8
License-File: LICENSE
Requires-Dist: falkordb>=1.0.0
Dynamic: license-file
